{
    "js": [
        "js/searchBuilder.bootstrap.js",
        "js/searchBuilder.bootstrap.min.js",
        "js/searchBuilder.bootstrap.min.mjs",
        "js/searchBuilder.bootstrap.mjs"
    ],
    "css": [
        "css/searchBuilder.bootstrap.css",
        "css/searchBuilder.bootstrap.min.css"
    ],
    "types": [
        "types/searchBuilder.bootstrap.d.ts"
    ],
    "src-repo": "http://github.com/DataTables/SearchBuilder",
    "last-tag": "1.8.4",
    "last-sync": "6b5447c0ffd9c7aca331876bfc0a03699a9ed726"
}