{
    "js": [
        "js/searchBuilder.bootstrap.js",
        "js/searchBuilder.bootstrap.min.js",
        "js/searchBuilder.bootstrap.min.mjs",
        "js/searchBuilder.bootstrap.mjs"
    ],
    "css": [
        "css/searchBuilder.bootstrap.css",
        "css/searchBuilder.bootstrap.min.css"
    ],
    "types": [
        "types/searchBuilder.bootstrap.d.ts"
    ],
    "src-repo": "http://github.com/DataTables/SearchBuilder",
    "last-tag": "1.8.3",
    "last-sync": "298179b2a25f2f616e93dbc64cd42b9b4008714a"
}